j2htmx/__init__.py
j2htmx/page.py
j2htmx/page_errors.py
j2htmx/version
j2htmx/version.py
j2htmx-0.1.0.dist-info/LICENSE
j2htmx-0.1.0.dist-info/METADATA
j2htmx-0.1.0.dist-info/WHEEL
j2htmx-0.1.0.dist-info/top_level.txt
j2htmx-0.1.0.dist-info/RECORD
