Metadata-Version: 2.1
Name: j2htmx
Version: 0.1.0
Summary: jinja2 template for light-weight htmx page rendering
Home-page: https://github.com/ko10ok/j2htmx
Author: Yuriy Sagitov
Author-email: pro100.ko10ok@gmail.com
License: Apache-2.0
Classifier: License :: OSI Approved :: Apache Software License
Classifier: Programming Language :: Python :: 3.10
Requires-Python: >=3.10.0
License-File: LICENSE
Requires-Dist: Jinja2 <4,>=3.1.3
